kedro_great_expectations/__about__.py
kedro_great_expectations/__init__.py
kedro_great_expectations-0.0.1.dist-info/METADATA
kedro_great_expectations-0.0.1.dist-info/WHEEL
kedro_great_expectations-0.0.1.dist-info/licenses/LICENSE.txt
kedro_great_expectations-0.0.1.dist-info/RECORD
